.dockerignore
.gitignore
CODE_OF_CONDUCT.md
MANIFEST.in
README.md
app.js
index.html
package-lock.json
package.json
setup.py
stencila-host.js
stencila.js
archive/kitchen-sink/fig1.jpg
archive/kitchen-sink/ice-cream-sales.xml
archive/kitchen-sink/manifest.xml
archive/kitchen-sink/manuscript.xml
archive/py-jupyter/bibliography.bibtex
archive/py-jupyter/manifest.xml
archive/py-jupyter/py-jupyter.ipynb
archive/py-jupyter/py-jupyter.ipynb.jats.xml
archive/r-markdown/bibliography.bibtex
archive/r-markdown/manifest.xml
archive/r-markdown/rmarkdown.Rmd
archive/r-markdown/rmarkdown.Rmd.jats.xml
binder/environment.yml
binder/install.R
binder/postBuild
binder/requirements.txt
binder/runtime.txt
nbstencilaproxy/__init__.py
nbstencilaproxy/handlers.py
nbstencilaproxy/package.json
nbstencilaproxy.egg-info/PKG-INFO
nbstencilaproxy.egg-info/SOURCES.txt
nbstencilaproxy.egg-info/dependency_links.txt
nbstencilaproxy.egg-info/requires.txt
nbstencilaproxy.egg-info/top_level.txt
nbstencilaproxy/static/tree.js